psair/__init__.py
psair/eda/EDADaemon.py
psair/eda/__init__.py
psair/eda/visualization.py
psair/etl/OutputManager.py
psair/etl/SQLDaemon.py
psair/etl/Table.py
psair/etl/__init__.py
psair/nlp/NLPmodel.py
psair/nlp/__init__.py
psair/nlp/data_processing.py
psair/nlp/preprocessing.py
psair/pipeline/PipelineManager.py
psair/pipeline/__init__.py
psair/utils/Tier.py
psair/utils/__init__.py
psair/utils/config_io.py
psair/utils/logger.py
psair-0.0.1a2.dist-info/licenses/LICENSE.txt
psair-0.0.1a2.dist-info/METADATA
psair-0.0.1a2.dist-info/WHEEL
psair-0.0.1a2.dist-info/top_level.txt
psair-0.0.1a2.dist-info/RECORD
