Metadata-Version: 2.4
Name: psair
Version: 0.0.1a2
Summary: Python Scaffolding for Analysis Itineraries in Research (PSAIR).
Author: Nick McCloskey
License: MIT
Project-URL: Repository, https://github.com/nmccloskey/PSAIR
Project-URL: Issues, https://github.com/nmccloskey/PSAIR/issues
Keywords: research,analysis,pipeline,nlp,linguistics
Classifier: Development Status :: 3 - Alpha
Classifier: Intended Audience :: Science/Research
Classifier: License :: OSI Approved :: MIT License
Classifier: Operating System :: OS Independent
Classifier: Programming Language :: Python :: 3
Classifier: Programming Language :: Python :: 3 :: Only
Classifier: Programming Language :: Python :: 3.10
Classifier: Programming Language :: Python :: 3.11
Classifier: Programming Language :: Python :: 3.12
Classifier: Topic :: Scientific/Engineering
Classifier: Topic :: Text Processing :: Linguistic
Requires-Python: >=3.12
License-File: LICENSE.txt
Requires-Dist: numpy<1.28,>=1.23
Requires-Dist: pandas<2.3,>=2.2
Requires-Dist: PyYAML<7.0,>=6.0
Requires-Dist: scikit-learn<1.7,>=1.6
Requires-Dist: scipy<1.16,>=1.10.1
Requires-Dist: matplotlib<3.11,>=3.10
Requires-Dist: seaborn<0.14,>=0.13
Requires-Dist: tqdm<5.0,>=4.67
Requires-Dist: openpyxl<3.2,>=3.1
Requires-Dist: PyPDF2<3.1,>=3.0
Requires-Dist: svglib<2.0,>=1.5
Requires-Dist: reportlab<5.0,>=4.3
Requires-Dist: spacy<4.0,>=3.8
Requires-Dist: benepar<0.3,>=0.2
Requires-Dist: nltk<4.0,>=3.9
Requires-Dist: docx2txt<1.0,>=0.8
Dynamic: license-file
